{"parent": "item/handheld","textures": {"layer0": "item/iron_hoe"},"overrides": [{ "predicate": {"damaged": 0, "damage": 0}, "model": "item/iron2"},
{ "predicate": {"damaged": 0, "damage": 0.004}, "model": "item/mob/mage_1"},
{ "predicate": {"damaged": 0, "damage": 0.008}, "model": "item/mob/blight_moving_1"},
{ "predicate": {"damaged": 0, "damage": 0.012}, "model": "item/mob/brazen_still_1"},
{ "predicate": {"damaged": 0, "damage": 0.016}, "model": "item/mob/brazen_moving_1"},
{ "predicate": {"damaged": 0, "damage": 0.02}, "model": "item/mob/bullant_still_1"},
{ "predicate": {"damaged": 0, "damage": 0.024}, "model": "item/mob/bullant_moving_1"},
{ "predicate": {"damaged": 0, "damage": 0.028}, "model": "item/mob/dweller_still_1"},
{ "predicate": {"damaged": 0, "damage": 0.032}, "model": "item/mob/dweller_moving_1"},
{ "predicate": {"damaged": 0, "damage": 0.036}, "model": "item/mob/dweller_still_2"},
{ "predicate": {"damaged": 0, "damage": 0.04}, "model": "item/mob/dweller_moving_2"},
{ "predicate": {"damaged": 0, "damage": 0.044}, "model": "item/mob/dweller_still_3"},
{ "predicate": {"damaged": 0, "damage": 0.048}, "model": "item/mob/dweller_moving_3"},
{ "predicate": {"damaged": 0, "damage": 0.052}, "model": "item/mob/dwindler_1"},
{ "predicate": {"damaged": 0, "damage": 0.056}, "model": "item/mob/dwindler_2"},
{ "predicate": {"damaged": 0, "damage": 0.06}, "model": "item/mob/duskblood_still_1"},
{ "predicate": {"damaged": 0, "damage": 0.064}, "model": "item/mob/duskblood_moving_1"},
{ "predicate": {"damaged": 0, "damage": 0.068}, "model": "item/mob/duskblood_still_2"},
{ "predicate": {"damaged": 0, "damage": 0.072}, "model": "item/mob/duskblood_moving_2"},
{ "predicate": {"damaged": 0, "damage": 0.076}, "model": "item/mob/ent_still_1"},
{ "predicate": {"damaged": 0, "damage": 0.08}, "model": "item/mob/ent_moving_1"},
{ "predicate": {"damaged": 0, "damage": 0.084}, "model": "item/mob/ent_still_2"},
{ "predicate": {"damaged": 0, "damage": 0.088}, "model": "item/mob/ent_moving_2"},
{ "predicate": {"damaged": 0, "damage": 0.092}, "model": "item/mob/ent_still_3"},
{ "predicate": {"damaged": 0, "damage": 0.096}, "model": "item/mob/ent_moving_3"},
{ "predicate": {"damaged": 0, "damage": 0.1}, "model": "item/mob/glacer_still_1"},
{ "predicate": {"damaged": 0, "damage": 0.104}, "model": "item/mob/glacer_moving_1"},
{ "predicate": {"damaged": 0, "damage": 0.108}, "model": "item/mob/glacer_still_2"},
{ "predicate": {"damaged": 0, "damage": 0.112}, "model": "item/mob/glacer_moving_2"},
{ "predicate": {"damaged": 0, "damage": 0.116}, "model": "item/mob/greeder_1"},
{ "predicate": {"damaged": 0, "damage": 0.12}, "model": "item/mob/greeder_2"},
{ "predicate": {"damaged": 0, "damage": 0.124}, "model": "item/mob/havenwitcher_1"},
{ "predicate": {"damaged": 0, "damage": 0.128}, "model": "item/mob/lost_1"},
{ "predicate": {"damaged": 0, "damage": 0.132}, "model": "item/mob/mage_1"},
{ "predicate": {"damaged": 0, "damage": 0.136}, "model": "item/mob/netherknight_still_1"},
{ "predicate": {"damaged": 0, "damage": 0.14}, "model": "item/mob/netherknight_moving_1"},
{ "predicate": {"damaged": 0, "damage": 0.144}, "model": "item/mob/ogre_still_1"},
{ "predicate": {"damaged": 0, "damage": 0.148}, "model": "item/mob/ogre_moving_1"},
{ "predicate": {"damaged": 0, "damage": 0.152}, "model": "item/mob/ratch_1"},
{ "predicate": {"damaged": 0, "damage": 0.156}, "model": "item/mob/ratch_2"},
{ "predicate": {"damaged": 0, "damage": 0.16}, "model": "item/mob/sandskull_1"},
{ "predicate": {"damaged": 0, "damage": 0.164}, "model": "item/mob/sandskull_2"},
{ "predicate": {"damaged": 0, "damage": 0.168}, "model": "item/mob/scorpion_still_1"},
{ "predicate": {"damaged": 0, "damage": 0.172}, "model": "item/mob/scorpion_moving_1"},
{ "predicate": {"damaged": 0, "damage": 0.176}, "model": "item/mob/scorpion_still_2"},
{ "predicate": {"damaged": 0, "damage": 0.18}, "model": "item/mob/scorpion_moving_2"},
{ "predicate": {"damaged": 0, "damage": 0.184}, "model": "item/mob/siccitas_still_1"},
{ "predicate": {"damaged": 0, "damage": 0.188}, "model": "item/mob/siccitas_moving_1"},
{ "predicate": {"damaged": 0, "damage": 0.192}, "model": "item/mob/skitter_still_1"},
{ "predicate": {"damaged": 0, "damage": 0.196}, "model": "item/mob/skitter_moving_1"},
{ "predicate": {"damaged": 0, "damage": 0.2}, "model": "item/mob/wanderer_1"},
{ "predicate": {"damaged": 0, "damage": 0.204}, "model": "item/mob/yeti_still_1"},
{ "predicate": {"damaged": 0, "damage": 0.208}, "model": "item/mob/yeti_moving_1"},
{ "predicate": {"damaged": 0, "damage": 1}, "model": "item/bright_relic"},{ "predicate": {"damaged": 1, "damage": 0}, "model": "item/iron2"}]}